MANIFEST.in
README.rst
setup.py
crunchable/__init__.py
crunchable/crunchable.py
crunchable.egg-info/PKG-INFO
crunchable.egg-info/SOURCES.txt
crunchable.egg-info/dependency_links.txt
crunchable.egg-info/not-zip-safe
crunchable.egg-info/requires.txt
crunchable.egg-info/top_level.txt