Metadata-Version: 1.0
Name: crunchable
Version: 0.2
Summary: Python SDK for Crunchable.IO
Home-page: UNKNOWN
Author: Crunchable.IO
Author-email: admin@crunchable.io
License: UNKNOWN
Platform: UNKNOWN
